odoo/addons/so_line_open_form/README.rst
odoo/addons/so_line_open_form/__init__.py
odoo/addons/so_line_open_form/__manifest__.py
odoo/addons/so_line_open_form/static/description/icon.png
odoo/addons/so_line_open_form/views/sale_views.xml
odoo_addon_so_line_open_form-16.0.1.0.0.2.dist-info/METADATA
odoo_addon_so_line_open_form-16.0.1.0.0.2.dist-info/WHEEL
odoo_addon_so_line_open_form-16.0.1.0.0.2.dist-info/top_level.txt
odoo_addon_so_line_open_form-16.0.1.0.0.2.dist-info/RECORD
